torch_fourier_slice/__init__.py
torch_fourier_slice/_dft_utils.py
torch_fourier_slice/backproject.py
torch_fourier_slice/project.py
torch_fourier_slice/volume_utils.py
torch_fourier_slice/_grids/__init__.py
torch_fourier_slice/_grids/_central_line_fftfreq_grid.py
torch_fourier_slice/_grids/_central_slice_fftfreq_grid.py
torch_fourier_slice/_grids/_ewald_curvature.py
torch_fourier_slice/slice_extraction/__init__.py
torch_fourier_slice/slice_extraction/_extract_central_slices_rfft_2d.py
torch_fourier_slice/slice_extraction/_extract_central_slices_rfft_3d.py
torch_fourier_slice/slice_insertion/__init__.py
torch_fourier_slice/slice_insertion/_insert_central_slices_rfft_3d.py
torch_fourier_slice-0.4.0.dist-info/METADATA
torch_fourier_slice-0.4.0.dist-info/WHEEL
torch_fourier_slice-0.4.0.dist-info/licenses/LICENSE
torch_fourier_slice-0.4.0.dist-info/RECORD
