Metadata-Version: 2.4
Name: torch-fourier-slice
Version: 0.4.0
Summary: Fourier slice extraction/insertion in PyTorch.
Project-URL: homepage, https://github.com/alisterburt/torch-fourier-slice
Project-URL: repository, https://github.com/alisterburt/torch-fourier-slice
Author-email: Alister Burt <alisterburt@gmail.com>
License: BSD-3-Clause
License-File: LICENSE
Classifier: Development Status :: 3 - Alpha
Classifier: License :: OSI Approved :: BSD License
Classifier: Programming Language :: Python :: 3
Classifier: Programming Language :: Python :: 3.10
Classifier: Programming Language :: Python :: 3.11
Classifier: Programming Language :: Python :: 3.12
Classifier: Programming Language :: Python :: 3.13
Classifier: Typing :: Typed
Requires-Python: >=3.10
Requires-Dist: einops
Requires-Dist: numpy
Requires-Dist: torch
Requires-Dist: torch-fourier-filter
Requires-Dist: torch-grid-utils>=0.0.8
Requires-Dist: torch-image-interpolation>=0.0.7
Provides-Extra: dev
Requires-Dist: ipython; extra == 'dev'
Requires-Dist: mypy; extra == 'dev'
Requires-Dist: pdbpp; extra == 'dev'
Requires-Dist: pre-commit; extra == 'dev'
Requires-Dist: rich; extra == 'dev'
Requires-Dist: ruff; extra == 'dev'
Provides-Extra: test
Requires-Dist: matplotlib; extra == 'test'
Requires-Dist: pytest; extra == 'test'
Requires-Dist: pytest-cov; extra == 'test'
Requires-Dist: scipy; extra == 'test'
Requires-Dist: torch-fourier-shell-correlation; extra == 'test'
Requires-Dist: ttsim3d; extra == 'test'
